{
  "name": "Torneio de Jiu-Jitsu 2024",
  "location": "São Paulo, Brazil",
  "date": "2024-08-15",
  "matches": [
    {
      "roundTitle": "Quarterfinals",
      "matches": [
        {
          "fighters": [
            {
              "name": "João Silva",
              "team": {
                "name": "Gracie Barra",
                "logo": "https://placehold.co/32"
              },
              "weightClass": "Leve",
              "beltRank": "Azul"
            },
            {
              "name": "Maria Souza",
              "team": {
                "name": "Alliance Jiu-Jitsu",
                "logo": "https://placehold.co/32"
              },
              "weightClass": "Leve",
              "beltRank": "Roxa"
            }
          ],
          "date": "2024-08-15T10:00:00Z",
          "winner": {
            "name": "João Silva",
            "team": {
              "name": "Gracie Barra",
              "logo": "https://placehold.co/32"
            },
            "weightClass": "Leve",
            "beltRank": "Azul"
          }
        },
        {
          "fighters": [
            {
              "name": "Pedro Santos",
              "team": {
                "name": "Checkmat",
                "logo": "https://placehold.co/32"
              },
              "weightClass": "Médio",
              "beltRank": "Marrom"
            },
            {
              "name": "Ana Oliveira",
              "team": {
                "name": "Atos Jiu-Jitsu",
                "logo": "https://placehold.co/32"
              },
              "weightClass": "Médio",
              "beltRank": "Azul"
            }
          ],
          "date": "2024-08-15T10:00:00Z",
          "winner": {
            "name": "Ana Oliveira",
            "team": {
              "name": "Atos Jiu-Jitsu",
              "logo": "https://placehold.co/32"
            },
            "weightClass": "Médio",
            "beltRank": "Azul"
          }
        },
        {
          "fighters": [
            {
              "name": "Rafael Mendes",
              "team": {
                "name": "Atos Jiu-Jitsu",
                "logo": "https://placehold.co/32"
              },
              "weightClass": "Pena",
              "beltRank": "Preta"
            },
            {
              "name": "Gabriela Garcia",
              "team": {
                "name": "Checkmat",
                "logo": "https://placehold.co/32"
              },
              "weightClass": "Pena",
              "beltRank": "Preta"
            }
          ],
          "date": "2024-08-15T10:00:00Z",
          "winner": {
            "name": "Rafael Mendes",
            "team": {
              "name": "Atos Jiu-Jitsu",
              "logo": "https://placehold.co/32"
            },
            "weightClass": "Pena",
            "beltRank": "Preta"
          }
        },
        {
          "fighters": [
            {
              "name": "Lucas Souza",
              "team": {
                "name": "Gracie Barra",
                "logo": "https://placehold.co/32"
              },
              "weightClass": "Leve",
              "beltRank": "Preta"
            },
            {
              "name": "Juliana Lima",
              "team": {
                "name": "Alliance Jiu-Jitsu",
                "logo": "https://placehold.co/32"
              },
              "weightClass": "Leve",
              "beltRank": "Preta"
            }
          ],
          "date": "2024-08-15T10:00:00Z",
          "winner": {
            "name": "Lucas Souza",
            "team": {
              "name": "Gracie Barra",
              "logo": "https://placehold.co/32"
            },
            "weightClass": "Leve",
            "beltRank": "Preta"
          }
        }
      ]
    },
    {
      "roundTitle": "Semifinals",
      "matches": [
        {
          "fighters": [
            {
              "name": "João Silva",
              "team": {
                "name": "Gracie Barra",
                "logo": "https://placehold.co/32"
              },
              "weightClass": "Leve",
              "beltRank": "Azul"
            },
            {
              "name": "Ana Oliveira",
              "team": {
                "name": "Atos Jiu-Jitsu",
                "logo": "https://placehold.co/32"
              },
              "weightClass": "Médio",
              "beltRank": "Azul"
            }
          ],
          "date": "2024-08-15T14:00:00Z",
          "winner": {
            "name": "Ana Oliveira",
            "team": {
              "name": "Atos Jiu-Jitsu",
              "logo": "https://placehold.co/32"
            },
            "weightClass": "Médio",
            "beltRank": "Azul"
          }
        },
        {
          "fighters": [
            {
              "name": "Rafael Mendes",
              "team": {
                "name": "Atos Jiu-Jitsu",
                "logo": "https://placehold.co/32"
              },
              "weightClass": "Pena",
              "beltRank": "Preta"
            },
            {
              "name": "Lucas Souza",
              "team": {
                "name": "Gracie Barra",
                "logo": "https://placehold.co/32"
              },
              "weightClass": "Leve",
              "beltRank": "Preta"
            }
          ],
          "date": "2024-08-15T14:00:00Z",
          "winner": {
            "name": "Rafael Mendes",
            "team": {
              "name": "Atos Jiu-Jitsu",
              "logo": "https://placehold.co/32"
            },
            "weightClass": "Pena",
            "beltRank": "Preta"
          }
        }
      ]
    },
    {
      "roundTitle": "Bronze Medal Game",
      "matches": [
        {
          "fighters": [
            {
              "name": "João Silva",
              "team": {
                "name": "Gracie Barra",
                "logo": "https://placehold.co/32"
              },
              "weightClass": "Leve",
              "beltRank": "Azul"
            },
            {
              "name": "Lucas Souza",
              "team": {
                "name": "Gracie Barra",
                "logo": "https://placehold.co/32"
              },
              "weightClass": "Leve",
              "beltRank": "Preta"
            }
          ],
          "date": "2024-08-15T16:00:00Z",
          "winner": {
            "name": "Lucas Souza",
            "team": {
              "name": "Gracie Barra",
              "logo": "https://placehold.co/32"
            },
            "weightClass": "Leve",
            "beltRank": "Preta"
          }
        }
      ]
    },
    {
      "roundTitle": "Gold Medal Game",
      "matches": [
        {
          "fighters": [
            {
              "name": "Ana Oliveira",
              "team": {
                "name": "Atos Jiu-Jitsu",
                "logo": "https://placehold.co/32"
              },
              "weightClass": "Médio",
              "beltRank": "Azul"
            },
            {
              "name": "Rafael Mendes",
              "team": {
                "name": "Atos Jiu-Jitsu",
                "logo": "https://placehold.co/32"
              },
              "weightClass": "Pena",
              "beltRank": "Preta"
            }
          ],
          "date": "2024-08-15T18:00:00Z",
          "winner": {
            "name": "Rafael Mendes",
            "team": {
              "name": "Atos Jiu-Jitsu",
              "logo": "https://placehold.co/32"
            },
            "weightClass": "Pena",
            "beltRank": "Preta"
          }
        }
      ]
    }
  ]
}